RubiksBlindfolded/__init__.py
RubiksBlindfolded/algorithm.py
RubiksBlindfolded/corner.py
RubiksBlindfolded/edge.py
RubiksBlindfolded-1.0.4.dist-info/LICENSE
RubiksBlindfolded-1.0.4.dist-info/METADATA
RubiksBlindfolded-1.0.4.dist-info/WHEEL
RubiksBlindfolded-1.0.4.dist-info/top_level.txt
RubiksBlindfolded-1.0.4.dist-info/RECORD
