Metadata-Version: 2.1
Name: RubiksBlindfolded
Version: 1.0.4
Summary: A Python package of solving Rubik's Cube in Blindfolded technique.
Home-page: https://github.com/mn-banjar/RubiksBlindfolded
Author: Moneera Banjar
Author-email: mn.banjar@gmail.com
License: MIT
Platform: UNKNOWN
Classifier: License :: OSI Approved :: MIT License
Classifier: Programming Language :: Python :: 3
